nicescad/__init__.py
nicescad/blockscad_converter.py
nicescad/nicescad_cmd.py
nicescad/openscad.py
nicescad/process.py
nicescad/solidservice.py
nicescad/version.py
nicescad/webserver.py
nicescad/web/static/css/pygments.css
nicescad_examples/nicescad_logo.scad
nicescad_examples/blockscad/A10BedLevelKnob.xml
nicescad_examples/blockscad/cube.xml
nicescad_examples/blockscad/cylinder.xml
nicescad_examples/blockscad/sphere.xml
nicescad_examples/scad/blockscad_converted/A10BedLevelKnob.scad
nicescad_examples/scad/blockscad_converted/cube.scad
nicescad_examples/scad/blockscad_converted/cylinder.scad
nicescad_examples/scad/blockscad_converted/sphere.scad
nicescad_examples/scad/openscad_examples/intersection.scad
nicescad_examples/scad/openscad_examples/openjscad_logo.scad
nicescad_examples/scad/openscad_examples/openjscad_logo.stl
nicescad_examples/scad/openscad_examples/Advanced/GEB.scad
nicescad_examples/scad/openscad_examples/Advanced/advance_intersection.scad
nicescad_examples/scad/openscad_examples/Advanced/animation.scad
nicescad_examples/scad/openscad_examples/Advanced/demo_cut.scad
nicescad_examples/scad/openscad_examples/Advanced/difference.scad
nicescad_examples/scad/openscad_examples/Advanced/fractal.scad
nicescad_examples/scad/openscad_examples/Advanced/intersecting.scad
nicescad_examples/scad/openscad_examples/Advanced/iteration.scad
nicescad_examples/scad/openscad_examples/Advanced/module_recursion.scad
nicescad_examples/scad/openscad_examples/Advanced/offset.scad
nicescad_examples/scad/openscad_examples/Advanced/search.scad
nicescad_examples/scad/openscad_examples/Advanced/translation.scad
nicescad_examples/scad/openscad_examples/Basics/CSG-modules.scad
nicescad_examples/scad/openscad_examples/Basics/CSG.scad
nicescad_examples/scad/openscad_examples/Basics/LetterBlock.scad
nicescad_examples/scad/openscad_examples/Basics/children.scad
nicescad_examples/scad/openscad_examples/Basics/children_indexed.scad
nicescad-0.3.0.dist-info/METADATA
nicescad-0.3.0.dist-info/WHEEL
nicescad-0.3.0.dist-info/entry_points.txt
nicescad-0.3.0.dist-info/licenses/LICENSE
nicescad-0.3.0.dist-info/RECORD
