Metadata-Version: 2.4
Name: nicescad
Version: 0.3.0
Summary: nicescad brings OpenScad to the browser (again)
Project-URL: Home, https://github.com/WolfgangFahl/nicescad
Project-URL: Documentation, https://wiki.bitplan.com/index.php/nicescad
Project-URL: Source, https://github.com/WolfgangFahl/nicescad
Author-email: Wolfgang Fahl <wf@bitplan.com>
Maintainer-email: Wolfgang Fahl <wf@bitplan.com>
License-Expression: Apache-2.0
License-File: LICENSE
Keywords: 3D-printing,nicegui,openscad,scad
Classifier: Development Status :: 4 - Beta
Classifier: Environment :: Web Environment
Classifier: Intended Audience :: Developers
Classifier: Intended Audience :: Education
Classifier: Intended Audience :: Science/Research
Classifier: License :: OSI Approved :: Apache Software License
Classifier: Operating System :: OS Independent
Classifier: Programming Language :: Python :: 3 :: Only
Classifier: Programming Language :: Python :: 3.10
Classifier: Programming Language :: Python :: 3.11
Classifier: Programming Language :: Python :: 3.12
Classifier: Programming Language :: Python :: 3.13
Classifier: Topic :: Software Development :: Libraries :: Python Modules
Requires-Python: >=3.10
Requires-Dist: ngwidgets>=0.26.0
Requires-Dist: nicegui>=2.20.0
Requires-Dist: openai
Requires-Dist: pydantic>=1.8.2
Requires-Dist: pygments
Requires-Dist: pywin32; platform_system == 'Windows'
Requires-Dist: requests
Requires-Dist: solidpython2>=2.0.2
Provides-Extra: test
Requires-Dist: green; extra == 'test'
